seabass/__init__.py
seabass/lmm_hier.py
seabass/screen_data.py
seabass-0.0.5.dist-info/LICENSE
seabass-0.0.5.dist-info/METADATA
seabass-0.0.5.dist-info/WHEEL
seabass-0.0.5.dist-info/top_level.txt
seabass-0.0.5.dist-info/RECORD
