Metadata-Version: 2.1
Name: seabass
Version: 0.0.5
Summary: A hierarchical linear mixed model for analyzing CRISPR screen data.
Home-page: https://github.com/daklab/seabass
Author: David A Knowles <daknowles@nygenome.org>
Project-URL: Bug Tracker, https://github.com/daklab/seabass/issues
Requires-Python: >=3.6
License-File: LICENSE
Requires-Dist: numpy (~=1.23)
Requires-Dist: torch (~=2.0)
Requires-Dist: pyro (~=1.8)
Requires-Dist: scipy (~=1.5)
Requires-Dist: statsmodels (~=0.14)
Requires-Dist: pandas (~=2.0)
